{
	"id": "tp1234",
	"name": "Test Paper 1",
	"audit": {
		"created_by": "1234",
		"created_on": "01-01-2016",
		"updated_by": "1234",
		"updated_on": "01-01-2016"

	},
	"status": "published",
	"data": [{
		"sno": 1,
		"type": "single_choice",
		"ques": "this is question 1",
		"option": ["india", "japan", "usa"],
		"answer": "india",
		"score_for_each_correct_ans": 1
	}, {
		"sno": 2,
		"type": "multiple_choice",
		"ques": "this is question 2",
		"option": ["india", "japan", "usa", "russia"],
		"answer": ["russia",
			"usa"
		],
		"score_for_each_correct_ans": 1
	}, {
		"sno": 3,
		"type": "fill_in_blanks",
		"ques": "this question contains blanks like ..... and ....",
		"answer": {
			"1": "first blank answer",
			"2": "second blank answer"
		},
		"score_for_each_correct_ans": 1
	}, {
		"sno": 4,
		"type": "true_or_false",
		"ques": "Delhi is capital of India",
		"answer": "true",
		"score_for_each_correct_ans": 1
	}, {
		"sno": 5,
		"type": "match",
		"match": {
			"left": {
				"1": "India",
				"2": "USA",
				"3": "Pakistan"
			},
			"right": {
				"1": "Hindu",
				"2": "Chirstian",
				"3": "Muslium"
			}
		},
		"answer": ["1-2", "2-3", "3-1"],
		"score_for_each_correct_ans": 1
	}, {
		"sno": 6,
		"type": "text",
		"ques": "who is gandhi",
		"keyword": ["1989", "india", "father-of-nation"],
		"score_for_each_correct_ans": 1
	}, {
		"sno": 7,
		"type": "multiple_choice_img",
		"is_q_img": "n",
		"is_q_img": "y",
		"ques": "who is gandhi in the following images",
		"option": ["img1", "img2", "img3", "img4"],
		"answer": ["img2",
			"img4"
		],
		"score_for_each_correct_ans": 1
	}]
}